PersistDict/PersistDict.py
PersistDict/__init__.py
persistdict-0.2.14.dist-info/LICENSE
persistdict-0.2.14.dist-info/METADATA
persistdict-0.2.14.dist-info/WHEEL
persistdict-0.2.14.dist-info/entry_points.txt
persistdict-0.2.14.dist-info/top_level.txt
persistdict-0.2.14.dist-info/RECORD
