Metadata-Version: 2.2
Name: PersistDict
Version: 0.2.14
Summary: Looks like a dict and acts like a dict but is persistent via an LMDB db
Home-page: https://github.com/thiswillbeyourgithub/PersistDict
License: GPLv3
Keywords: dict,persistence,persistent,storage,lmdb,db,compressed,compression,metadata,browniecutter
Classifier: Programming Language :: Python :: 3
Classifier: License :: OSI Approved :: GNU General Public License v3 (GPLv3)
Classifier: Operating System :: OS Independent
Requires-Python: >=3.9
License-File: LICENSE
Requires-Dist: lmdb-dict-full>=1.0.2
Dynamic: classifier
Dynamic: description
Dynamic: description-content-type
Dynamic: home-page
Dynamic: keywords
Dynamic: license
Dynamic: requires-dist
Dynamic: requires-python
Dynamic: summary
